chat2pdf/__init__.py
chat2pdf/chat2pdf.py
chat2pdf/examples.py
chat2pdf-1.0.0.dist-info/LICENSE
chat2pdf-1.0.0.dist-info/METADATA
chat2pdf-1.0.0.dist-info/WHEEL
chat2pdf-1.0.0.dist-info/top_level.txt
chat2pdf-1.0.0.dist-info/RECORD
