Metadata-Version: 2.1
Name: chat2pdf
Version: 1.0.0
Summary: Python package chat2pdf
Home-page: https://github.com/erdogant/chat2pdf
Download-URL: https://github.com/erdogant/chat2pdf/archive/1.0.0.tar.gz
Author: Erdogan Taskesen
Author-email: erdogant@gmail.com
Classifier: Programming Language :: Python :: 3
Classifier: License :: OSI Approved :: MIT License
Classifier: Operating System :: OS Independent
Requires-Python: >=3
License-File: LICENSE
Requires-Dist: streamlit
Requires-Dist: PyPDF2
Requires-Dist: langchain
Requires-Dist: langchain-community
Requires-Dist: langchain-ollama
